[{"date":"2021-02-05T19:00","name":"slides-imagens.zip","desc":"slides-imagens-daw","tipo":"cartaz","ext":"zip","nome":"Joao","id":"601d95c035dbc48eccc7507b"},{"date":"2021-02-05T19:06","name":"slides-imagens.zip","desc":"slides-imagens-daw2","tipo":"cartaz","ext":"zip","nome":"Joao","id":"601d973e35dbc48eccc7507c"},{"date":"2021-02-05T19:07","name":"slides-imagens.zip","desc":"slides-imagens-daw3","tipo":"cartaz","ext":"zip","nome":"Joao","id":"601d9762e8a8d3a504390908"},{"date":"2021-02-05T19:10","name":"slides-imagens.zip","desc":"slides-imagens-daw4","tipo":"cartaz","ext":"zip","nome":"Joao","id":"601d982d95929106f058a939"},{"date":"2021-02-05T19:12","name":"slides-imagens.zip","desc":"slides-imagens-daw5","tipo":"cartaz","ext":"zip","nome":"Joao","id":"601d98b46869c853c8a5dbfb"},{"date":"2021-02-05T19:36","name":"slides-trabalho-imagens.zip","desc":"slides-imagens-daw6","tipo":"cartaz","ext":"zip","nome":"Joao","id":"601d9e253bdf0b79243e9a83"},{"date":"2021-02-05T20:12","name":"bugs-bunny.zip","desc":"iamgens","tipo":"cartaz","ext":"jpg","nome":"Joao","id":"601da6c23bdf0b79243e9a84"},{"date":"2021-02-05T21:02","name":"slides-trabalho-imagens.zip","desc":"teste1","tipo":"teste","ext":"zip","nome":"Joao","id":"601db24f22b27a9520368e0d"},{"date":"2021-02-05T21:02","name":"slides-trabalho-imagens.zip","desc":"problema1","tipo":"problema","ext":"zip","nome":"Joao","id":"601db27922b27a9520368e0e"},{"date":"2021-02-05T21:03","name":"CG_Fase_4.zip","desc":"problema2","tipo":"problema","ext":"pdf","nome":"Joao","id":"601db29d22b27a9520368e0f"}]
